data_pipeline_tooling/__init__.py
data_pipeline_tooling/artifact_store.py
data_pipeline_tooling/orchestrator.py
data_pipeline_tooling/tooling.py
data_pipeline_tooling-0.15.data/scripts/orchestrator_cli
data_pipeline_tooling-0.15.dist-info/LICENSE
data_pipeline_tooling-0.15.dist-info/METADATA
data_pipeline_tooling-0.15.dist-info/WHEEL
data_pipeline_tooling-0.15.dist-info/top_level.txt
data_pipeline_tooling-0.15.dist-info/RECORD
