Metadata-Version: 2.1
Name: data-pipeline-tooling
Version: 0.15
Summary: A library for databricks jobs api
Home-page: https://github.com/JH-PMAP/data_pipeline_tooling
Author: Eric Schles
Author-email: eschles3@jh.edu
License: MIT
Classifier: License :: OSI Approved :: MIT License
Classifier: Programming Language :: Python :: 3
Classifier: Programming Language :: Python :: 3.8
Classifier: Programming Language :: Python :: 3.9
License-File: LICENSE
Requires-Dist: requests
Requires-Dist: fire
Requires-Dist: azure-storage-blob
Requires-Dist: azure-storage-file-datalake
Requires-Dist: azure-core
Requires-Dist: azure-storage-file-share
